tower_of_hanoi/__init__.py
tower_of_hanoi/hanoi.py
tower_of_hanoi-0.1.0.dist-info/LICENSE
tower_of_hanoi-0.1.0.dist-info/METADATA
tower_of_hanoi-0.1.0.dist-info/WHEEL
tower_of_hanoi-0.1.0.dist-info/top_level.txt
tower_of_hanoi-0.1.0.dist-info/RECORD
