Metadata-Version: 2.1
Name: tower-of-hanoi
Version: 0.1.0
Summary: forget the old method of tower of hanoi code.using this package you can get the output in 3 line of code
Author: Adarsh
Author-email: adarshmsg11@gmail.com
License-File: LICENSE
